{"users":{"User2":{"username":"User2","notifications":[],"comments":[{"commentText":"This is a reply","userName":"User2","commentID":1,"numberOfUpvotes":2,"timestamp":"Mar 14, 2018 11:51:25 AM","children":[],"isTopLevel":false}],"isAdmin":false},"User1":{"username":"User1","notifications":[{"notificationText":"UserUser1commented on your photo : commenttext","read":false,"notificationComment":{"commentText":"Hello","userName":"User1","commentID":0,"numberOfUpvotes":-1,"timestamp":"Mar 14, 2018 11:51:25 AM","children":[{"commentText":"This is a reply","userName":"User2","commentID":1,"numberOfUpvotes":2,"timestamp":"Mar 14, 2018 11:51:25 AM","children":[],"isTopLevel":false}],"isTopLevel":true}},{"notificationText":"UserUser2replied to your comment : This is a reply","read":false,"notificationComment":{"commentText":"This is a reply","userName":"User2","commentID":1,"numberOfUpvotes":2,"timestamp":"Mar 14, 2018 11:51:25 AM","children":[],"isTopLevel":false}},{"notificationText":"UserAdmincommented on your photo : commenttext","read":false,"notificationComment":{"commentText":"\"hi whats up\"","userName":"Admin","commentID":2,"numberOfUpvotes":0,"timestamp":"Mar 14, 2018 11:51:55 AM","children":[],"isTopLevel":true}},{"notificationText":"UserAdmincommented on your photo : commenttext","read":false,"notificationComment":{"commentText":"\"Did it really work?\"","userName":"Admin","commentID":3,"numberOfUpvotes":0,"timestamp":"Mar 14, 2018 11:52:23 AM","children":[],"isTopLevel":true}}],"comments":[{"commentText":"Hello","userName":"User1","commentID":0,"numberOfUpvotes":-1,"timestamp":"Mar 14, 2018 11:51:25 AM","children":[{"commentText":"This is a reply","userName":"User2","commentID":1,"numberOfUpvotes":2,"timestamp":"Mar 14, 2018 11:51:25 AM","children":[],"isTopLevel":false}],"isTopLevel":true}],"isAdmin":false},"User3":{"username":"User3","notifications":[],"comments":[],"isAdmin":false},"Admin":{"username":"Admin","notifications":[],"comments":[{"commentText":"\"hi whats up\"","userName":"Admin","commentID":2,"numberOfUpvotes":0,"timestamp":"Mar 14, 2018 11:51:55 AM","children":[],"isTopLevel":true},{"commentText":"\"Did it really work?\"","userName":"Admin","commentID":3,"numberOfUpvotes":0,"timestamp":"Mar 14, 2018 11:52:23 AM","children":[],"isTopLevel":true}],"isAdmin":true}},"photographs":{"User2":[{"ownerUserName":"User2","comments":[],"photographID":1}],"User1":[{"ownerUserName":"User1","comments":[{"commentText":"Hello","userName":"User1","commentID":0,"numberOfUpvotes":-1,"timestamp":"Mar 14, 2018 11:51:25 AM","children":[{"commentText":"This is a reply","userName":"User2","commentID":1,"numberOfUpvotes":2,"timestamp":"Mar 14, 2018 11:51:25 AM","children":[],"isTopLevel":false}],"isTopLevel":true},{"commentText":"\"hi whats up\"","userName":"Admin","commentID":2,"numberOfUpvotes":0,"timestamp":"Mar 14, 2018 11:51:55 AM","children":[],"isTopLevel":true},{"commentText":"\"Did it really work?\"","userName":"Admin","commentID":3,"numberOfUpvotes":0,"timestamp":"Mar 14, 2018 11:52:23 AM","children":[],"isTopLevel":true}],"photographID":0},{"ownerUserName":"User1","comments":[{"commentText":"Hello","userName":"User1","commentID":0,"numberOfUpvotes":-1,"timestamp":"Mar 14, 2018 11:51:25 AM","children":[{"commentText":"This is a reply","userName":"User2","commentID":1,"numberOfUpvotes":2,"timestamp":"Mar 14, 2018 11:51:25 AM","children":[],"isTopLevel":false}],"isTopLevel":true}],"photographID":0},{"ownerUserName":"User1","comments":[{"commentText":"Hello","userName":"User1","commentID":0,"numberOfUpvotes":-1,"timestamp":"Mar 14, 2018 11:51:25 AM","children":[{"commentText":"This is a reply","userName":"User2","commentID":1,"numberOfUpvotes":2,"timestamp":"Mar 14, 2018 11:51:25 AM","children":[],"isTopLevel":false}],"isTopLevel":true},{"commentText":"\"hi whats up\"","userName":"Admin","commentID":2,"numberOfUpvotes":0,"timestamp":"Mar 14, 2018 11:51:55 AM","children":[],"isTopLevel":true}],"photographID":0},{"ownerUserName":"User1","comments":[{"commentText":"Hello","userName":"User1","commentID":0,"numberOfUpvotes":-1,"timestamp":"Mar 14, 2018 11:51:25 AM","children":[{"commentText":"This is a reply","userName":"User2","commentID":1,"numberOfUpvotes":2,"timestamp":"Mar 14, 2018 11:51:25 AM","children":[],"isTopLevel":false}],"isTopLevel":true},{"commentText":"\"hi whats up\"","userName":"Admin","commentID":2,"numberOfUpvotes":0,"timestamp":"Mar 14, 2018 11:51:55 AM","children":[],"isTopLevel":true},{"commentText":"\"Did it really work?\"","userName":"Admin","commentID":3,"numberOfUpvotes":0,"timestamp":"Mar 14, 2018 11:52:23 AM","children":[],"isTopLevel":true}],"photographID":0}]},"IDgen":{"commentID":4,"photographID":2},"comments":{"0":{"commentText":"Hello","userName":"User1","commentID":0,"numberOfUpvotes":-1,"timestamp":"Mar 14, 2018 11:51:25 AM","children":[{"commentText":"This is a reply","userName":"User2","commentID":1,"numberOfUpvotes":2,"timestamp":"Mar 14, 2018 11:51:25 AM","children":[],"isTopLevel":false}],"isTopLevel":true},"1":{"commentText":"This is a reply","userName":"User2","commentID":1,"numberOfUpvotes":2,"timestamp":"Mar 14, 2018 11:51:25 AM","children":[],"isTopLevel":false},"2":{"commentText":"\"hi whats up\"","userName":"Admin","commentID":2,"numberOfUpvotes":0,"timestamp":"Mar 14, 2018 11:51:55 AM","children":[],"isTopLevel":true},"3":{"commentText":"\"Did it really work?\"","userName":"Admin","commentID":3,"numberOfUpvotes":0,"timestamp":"Mar 14, 2018 11:52:23 AM","children":[],"isTopLevel":true}}}